format_def_indent/__init__.py
format_def_indent/_base_fixer.py
format_def_indent/_helper.py
format_def_indent/_main_jupyter.py
format_def_indent/_main_py.py
format_def_indent-0.1.7.dist-info/LICENSE
format_def_indent-0.1.7.dist-info/METADATA
format_def_indent-0.1.7.dist-info/WHEEL
format_def_indent-0.1.7.dist-info/entry_points.txt
format_def_indent-0.1.7.dist-info/top_level.txt
format_def_indent-0.1.7.dist-info/RECORD
