Metadata-Version: 2.1
Name: format-def-indent
Version: 0.1.7
Summary: Make sure arguments in Python function definitions are indented by 8 spaces
Home-page: https://github.com/cyyc1/py-def-indent-formatter
License: MIT
Classifier: License :: OSI Approved :: MIT License
Classifier: Programming Language :: Python :: 3
Classifier: Programming Language :: Python :: 3 :: Only
Requires-Python: >=3.8
License-File: LICENSE
Requires-Dist: jupyter-notebook-parser (>=0.1.4)
Requires-Dist: tokenize-rt (>=3.0.1)
